google_alert/__init__.py
google_alert/browser.py
google_alert/monitor_chron.py
google_alert/sensor_db.py
google_alert-0.1.2.dist-info/METADATA
google_alert-0.1.2.dist-info/WHEEL
google_alert-0.1.2.dist-info/RECORD
