Metadata-Version: 2.4
Name: google-alert
Version: 0.1.2
Summary: A Python library for sending temperature alerts via Chromecast devices
Author-email: Emir <emir@example.com>
License: MIT
Keywords: alerts,chromecast,iot,monitoring,temperature
Classifier: Development Status :: 4 - Beta
Classifier: Intended Audience :: Developers
Classifier: License :: OSI Approved :: MIT License
Classifier: Programming Language :: Python :: 3
Classifier: Programming Language :: Python :: 3.11
Classifier: Programming Language :: Python :: 3.12
Classifier: Programming Language :: Python :: 3.13
Classifier: Topic :: Home Automation
Classifier: Topic :: System :: Monitoring
Requires-Python: >=3.11
Requires-Dist: orjson>=3.10.18
Requires-Dist: pychromecast>=14.0.7
Provides-Extra: dev
Requires-Dist: pytest>=7.0.0; extra == 'dev'
